{"skeleton":{"hash":"nLI5wObIMxO1LW42l9LDAR2b5hU","spine":"3.6.52","width":1920,"height":1080},"bones":[{"name":"root"}],"slots":[{"name":"bloodA","bone":"root","attachment":"bloodA"},{"name":"bloodB","bone":"root","attachment":"bloodB"},{"name":"bloodC","bone":"root","attachment":"bloodC"}],"skins":{"default":{"bloodA":{"bloodA":{"width":1920,"height":1080}},"bloodB":{"bloodB":{"width":1920,"height":1080}},"bloodC":{"bloodC":{"width":1920,"height":1080}}}},"animations":{"muerto":{"slots":{"bloodA":{"color":[{"time":0,"color":"ffffff00","curve":"stepped"},{"time":0.4333,"color":"ffffff00"},{"time":1.2333,"color":"ffffffff"}]},"bloodB":{"color":[{"time":0,"color":"ffffff00","curve":"stepped"},{"time":0.2667,"color":"ffffff00"},{"time":0.4667,"color":"ffffffff"}]},"bloodC":{"color":[{"time":0,"color":"ffffff00"},{"time":0.2667,"color":"ffffffff"}]}}},"simple":{"slots":{"bloodA":{"color":[{"time":0,"color":"ffffff00","curve":"stepped"},{"time":0.4333,"color":"ffffff00"},{"time":1.2333,"color":"ffffffff"},{"time":2.8333,"color":"ffffff00"}]},"bloodB":{"color":[{"time":0,"color":"ffffff00","curve":"stepped"},{"time":0.2667,"color":"ffffff00"},{"time":0.4667,"color":"ffffffff","curve":"stepped"},{"time":1.2333,"color":"ffffffff"},{"time":1.8667,"color":"ffffff00"}]},"bloodC":{"color":[{"time":0,"color":"ffffff00"},{"time":0.2667,"color":"ffffffff","curve":"stepped"},{"time":1.2333,"color":"ffffffff"},{"time":2.1667,"color":"ffffff00"}]}}}}}